setup.py
cheffab/__init__.py
cheffab/base.py
cheffab/exceptions.py
cheffab.egg-info/PKG-INFO
cheffab.egg-info/SOURCES.txt
cheffab.egg-info/dependency_links.txt
cheffab.egg-info/not-zip-safe
cheffab.egg-info/requires.txt
cheffab.egg-info/top_level.txt
cheffab/events/__init__.py
cheffab/events/base.py
cheffab/events/graphite.py
cheffab/events/sendgrid.py
cheffab/tests/__init__.py
cheffab/tests/test_base.py