Metadata-Version: 1.1
Name: cheffab
Version: 0.0.2
Summary: Fabric wrapper for chef integration
Home-page: http://github.com/mopub/cheffab
Author: Rob McQueen
Author-email: rob@mopub.com
License: Apache 2.0
Platform: UNKNOWN
Classifier: Development Status :: 3 - Alpha
Classifier: License :: OSI Approved :: Apache Software License
Classifier: Natural Language :: English
Classifier: Operating System :: OS Independent
Classifier: Programming Language :: Python
